mdparser/__init__.py
mdparser/cli.py
mdparser/core.py
mdparser/parsers/__init__.py
mdparser/parsers/ast/__init__.py
mdparser/parsers/ast/node.py
mdparser/parsers/ast/parser.py
mdparser/parsers/ast/render.py
mdparser/parsers/ast/test.py
mdparser/parsers/ast/tokenizer.py
mdparser/parsers/htmlParser/__init__.py
mdparser/parsers/htmlParser/parse.py
mdparser_html-2.0.2.dist-info/licenses/LICENSE
mdparser_html-2.0.2.dist-info/METADATA
mdparser_html-2.0.2.dist-info/WHEEL
mdparser_html-2.0.2.dist-info/entry_points.txt
mdparser_html-2.0.2.dist-info/top_level.txt
mdparser_html-2.0.2.dist-info/RECORD
