Metadata-Version: 2.4
Name: mdparser-html
Version: 2.0.2
Summary: mdparser-html is a lightweight and extensible Markdown → HTML converter with a clean Python API and CLI.
Author: Tarun
License-Expression: MIT
Project-URL: Documentation, https://mdparser.tarunnayaka.me
Project-URL: Homepage, https://github.com/Rtarun3606k/mdparser
Project-URL: Source, https://github.com/Rtarun3606k/mdparser
Project-URL: Issues, https://github.com/Rtarun3606k/mdparser/issues
Project-URL: Changelog, https://github.com/Rtarun3606k/mdparser/blob/main/CHANGELOG.md
Project-URL: Author, https://tarunnayaka.me
Requires-Python: >=3.8
License-File: LICENSE
Dynamic: license-file
